pydantic_gbnf_grammar_generator/__init__.py
pydantic_gbnf_grammar_generator/main.py
pydantic_gbnf_gammar_generator-0.1.0.dist-info/LICENSE
pydantic_gbnf_gammar_generator-0.1.0.dist-info/METADATA
pydantic_gbnf_gammar_generator-0.1.0.dist-info/WHEEL
pydantic_gbnf_gammar_generator-0.1.0.dist-info/top_level.txt
pydantic_gbnf_gammar_generator-0.1.0.dist-info/RECORD
