Metadata-Version: 2.1
Name: pydantic_gbnf_gammar_generator
Version: 0.1.0
Summary: Generates GBNF grammars from pydantic models
Author-email: Ruben Hohndorf <ruben.hohndorf@gmail.com>
Project-URL: Homepage, https://github.com/rhohndorf/pydantic-gbnf-gammar-generator
Project-URL: Issues, https://github.com/rhohndorf/pydantic-gbnf-gammar-generator/issues
Classifier: Programming Language :: Python :: 3
Classifier: License :: OSI Approved :: MIT License
Classifier: Operating System :: OS Independent
Requires-Python: >=3.10
License-File: LICENSE
Requires-Dist: pydantic >=2.5.3
Requires-Dist: docstring-parser ==0.16
